jsonwiz/__init__.py
jsonwiz-0.0.1.dist-info/LICENSE
jsonwiz-0.0.1.dist-info/METADATA
jsonwiz-0.0.1.dist-info/WHEEL
jsonwiz-0.0.1.dist-info/entry_points.txt
jsonwiz-0.0.1.dist-info/top_level.txt
jsonwiz-0.0.1.dist-info/RECORD
