Metadata-Version: 2.1
Name: jsonwiz
Version: 0.0.1
Summary: A command line tool to manipulate JSON files.
Home-page: https://github.com/karishmashuklaa/jsonwiz
Author: Karishma Shukla
Author-email: karishmashuklaa@gmail.com
License: MIT
Keywords: json,cli,command line,command line interface,json files,json manipulation,jsoncli,jsoncli tool,jsoncli command line tool,jsoncli command line interface,jsonwiz,jsonwiz tool,jsoncli command line
Classifier: Intended Audience :: Developers
Classifier: Programming Language :: Python :: 3
Classifier: Operating System :: Unix
Classifier: Operating System :: MacOS :: MacOS X
Classifier: Operating System :: Microsoft :: Windows
License-File: LICENSE
